deplicate-1.2.3.dist-info/DESCRIPTION.rst
deplicate-1.2.3.dist-info/METADATA
deplicate-1.2.3.dist-info/RECORD
deplicate-1.2.3.dist-info/WHEEL
deplicate-1.2.3.dist-info/metadata.json
deplicate-1.2.3.dist-info/top_level.txt
deplicate-1.2.3.dist-info/zip-safe
duplicate/__init__.py
duplicate/core.py
duplicate/deplicate.py
duplicate/structs.py
