Metadata-Version: 2.0
Name: deplicate
Version: 1.2.3
Summary: Advanced Duplicate File Finder for Python. Nothing is impossible to solve.
Home-page: https://github.com/deplicate/deplicate
Author: Walter Purcaro
Author-email: vuolter@gmail.com
License: MIT
Download-URL: https://github.com/deplicate/deplicate/releases
Keywords: duplicate duplicatefinder duplicates dups
Platform: any
Classifier: Development Status :: 5 - Production/Stable
Classifier: Intended Audience :: Developers
Classifier: Intended Audience :: End Users/Desktop
Classifier: License :: OSI Approved :: MIT License
Classifier: Natural Language :: English
Classifier: Operating System :: MacOS :: MacOS X
Classifier: Operating System :: Microsoft :: Windows
Classifier: Operating System :: POSIX
Classifier: Programming Language :: Python
Classifier: Programming Language :: Python :: 2
Classifier: Programming Language :: Python :: 2.6
Classifier: Programming Language :: Python :: 2.7
Classifier: Programming Language :: Python :: 3
Classifier: Programming Language :: Python :: 3.3
Classifier: Programming Language :: Python :: 3.4
Classifier: Programming Language :: Python :: 3.5
Classifier: Programming Language :: Python :: 3.6
Classifier: Topic :: Software Development :: Libraries :: Python Modules
Classifier: Topic :: System
Classifier: Topic :: System :: Filesystems
Classifier: Topic :: Utilities
Requires-Python: >=2.6,!=3.0,!=3.1,!=3.2
Requires-Dist: psutil
Requires-Dist: send2trash
Requires-Dist: xxhash (>=1)
Requires-Dist: directio; os_name != "nt"
Requires-Dist: pypiwin32 (>=154); os_name == "nt"
Requires-Dist: enum34; python_version < "3.4"
Requires-Dist: scandir; python_version < "3.5"
Requires-Dist: pyobjc; sys_platform == "darwin"
Provides-Extra: cli
Requires-Dist: deplicate-cli; extra == 'cli'
Provides-Extra: full
Requires-Dist: deplicate-cli; extra == 'full'
